redis_benchmarks_specification/__api__/Readme.md
redis_benchmarks_specification/__api__/__init__.py
redis_benchmarks_specification/__api__/api.py
redis_benchmarks_specification/__api__/app.py
redis_benchmarks_specification/__builder__/Readme.md
redis_benchmarks_specification/__builder__/__init__.py
redis_benchmarks_specification/__builder__/builder.py
redis_benchmarks_specification/__builder__/schema.py
redis_benchmarks_specification/__cli__/__init__.py
redis_benchmarks_specification/__cli__/args.py
redis_benchmarks_specification/__cli__/cli.py
redis_benchmarks_specification/__cli__/stats.py
redis_benchmarks_specification/__common__/__init__.py
redis_benchmarks_specification/__common__/builder_schema.py
redis_benchmarks_specification/__common__/env.py
redis_benchmarks_specification/__common__/github.py
redis_benchmarks_specification/__common__/package.py
redis_benchmarks_specification/__common__/runner.py
redis_benchmarks_specification/__common__/spec.py
redis_benchmarks_specification/__common__/suppress_warnings.py
redis_benchmarks_specification/__common__/timeseries.py
redis_benchmarks_specification/__compare__/__init__.py
redis_benchmarks_specification/__compare__/args.py
redis_benchmarks_specification/__compare__/compare.py
redis_benchmarks_specification/__init__.py
redis_benchmarks_specification/__runner__/__init__.py
redis_benchmarks_specification/__runner__/args.py
redis_benchmarks_specification/__runner__/remote_profiling.py
redis_benchmarks_specification/__runner__/runner.py
redis_benchmarks_specification/__self_contained_coordinator__/__init__.py
redis_benchmarks_specification/__self_contained_coordinator__/args.py
redis_benchmarks_specification/__self_contained_coordinator__/artifacts.py
redis_benchmarks_specification/__self_contained_coordinator__/build_info.py
redis_benchmarks_specification/__self_contained_coordinator__/clients.py
redis_benchmarks_specification/__self_contained_coordinator__/cpuset.py
redis_benchmarks_specification-0.2.47.dist-info/LICENSE
redis_benchmarks_specification-0.2.47.dist-info/METADATA
redis_benchmarks_specification-0.2.47.dist-info/WHEEL
redis_benchmarks_specification-0.2.47.dist-info/entry_points.txt
redis_benchmarks_specification-0.2.47.dist-info/RECORD
