Metadata-Version: 2.1
Name: redis-benchmarks-specification
Version: 0.2.47
Summary: The Redis benchmarks specification describes the cross-language/tools requirements and expectations to foster performance and observability standards around redis related technologies. Members from both industry and academia, including organizations and individuals are encouraged to contribute.
Author: filipecosta90
Author-email: filipecosta.90@gmail.com
Requires-Python: >=3.10.0,<4.0.0
Classifier: Programming Language :: Python :: 3
Classifier: Programming Language :: Python :: 3.10
Classifier: Programming Language :: Python :: 3.11
Classifier: Programming Language :: Python :: 3.12
Requires-Dist: Flask (>=2.0.3,<3.0.0)
Requires-Dist: Flask-HTTPAuth (>=4.4.0,<5.0.0)
Requires-Dist: GitPython (>=3.1.20,<4.0.0)
Requires-Dist: PyGithub (>=1.55,<2.0)
Requires-Dist: PyYAML (>=6.0,<7.0)
Requires-Dist: argparse (>=1.4.0,<2.0.0)
Requires-Dist: docker (>=7.1.0,<8.0.0)
Requires-Dist: flask-restx (>=0.5.0,<0.6.0)
Requires-Dist: jsonpath-ng (>=1.6.1,<2.0.0)
Requires-Dist: marshmallow (>=3.12.2,<4.0.0)
Requires-Dist: node-semver (>=0.8.1,<0.9.0)
Requires-Dist: numpy (>=2.0.0,<3.0.0)
Requires-Dist: oyaml (>=1.0,<2.0)
Requires-Dist: pandas (>=2.1.2,<3.0.0)
Requires-Dist: psutil (>=5.9.4,<6.0.0)
Requires-Dist: redis (>=4.2.0,<5.0.0)
Requires-Dist: redisbench-admin (>=0.11.1,<0.12.0)
Requires-Dist: seaborn (>=0.13.2,<0.14.0)
Requires-Dist: semver (>=2.13.0,<3.0.0)
Requires-Dist: typed-ast (>=1.5.0,<2.0.0)
